subsbml/SimpleModel.py
subsbml/SimpleReaction.py
subsbml/Subsystem.py
subsbml/System.py
subsbml/__init__.py
subsbml/setIdFromNames.py
subsbml/utilityFunctions.py
subsbml-0.9.0.dist-info/LICENSE
subsbml-0.9.0.dist-info/METADATA
subsbml-0.9.0.dist-info/WHEEL
subsbml-0.9.0.dist-info/top_level.txt
subsbml-0.9.0.dist-info/RECORD
