Metadata-Version: 2.1
Name: subsbml
Version: 0.9.0
Summary: SBML subsystem interaction modeling toolbox in Python
Home-page: https://github.com/BuildACell/subsbml
Author: Ayush Pandey
Author-email: apandey@caltech.edu
License: UNKNOWN
Project-URL: Documentation, https://readthedocs.org/projects/subsbml/
Project-URL: Source, https://github.com/BuildACell/subsbml
Project-URL: Tracker, https://github.com/BuildACell/subsbml/issues
Keywords: SBML Automated Model Reduction Modeling QSSA Hill functions
Platform: UNKNOWN
Classifier: Development Status :: 4 - Beta
Classifier: Intended Audience :: Science/Research
Classifier: Intended Audience :: Developers
Classifier: License :: OSI Approved :: BSD License
Classifier: Programming Language :: Python :: 3.6
Classifier: Topic :: Software Development
Classifier: Topic :: Scientific/Engineering
Classifier: Operating System :: OS Independent
Requires-Python: >=3.6
Requires-Dist: python-libsbml
Requires-Dist: scipy
Requires-Dist: numpy
Requires-Dist: matplotlib
